infi.git_mirror-0.0.12-py2.7-nspkg.pth
infi/git_mirror/__init__.py
infi/git_mirror/__version__.py
infi/git_mirror/scripts/__init__.py
infi.git_mirror-0.0.12.dist-info/LICENSE
infi.git_mirror-0.0.12.dist-info/METADATA
infi.git_mirror-0.0.12.dist-info/WHEEL
infi.git_mirror-0.0.12.dist-info/entry_points.txt
infi.git_mirror-0.0.12.dist-info/namespace_packages.txt
infi.git_mirror-0.0.12.dist-info/top_level.txt
infi.git_mirror-0.0.12.dist-info/RECORD
