Metadata-Version: 2.1
Name: infi.git-mirror
Version: 0.0.12
Summary: A simple console script for mirroring git repositories between two remotes.
Home-page: https://github.com/Infinidat/infi.git_mirror
Author: Arnon Yaari
Author-email: arnony@infinidat.com
License: BSD
Platform: UNKNOWN
Classifier: Intended Audience :: Developers
Classifier: Intended Audience :: System Administrators
Classifier: License :: OSI Approved :: BSD License
Classifier: Operating System :: OS Independent
Classifier: Programming Language :: Python
Classifier: Topic :: Software Development :: Libraries :: Python Modules
Requires-Dist: infi.execute
Requires-Dist: infi.pyutils
Requires-Dist: setuptools
